lazy_log/__init__.py
lazy_log/__main__.py
lazy_log/cli.py
lazy_log/constants.py
lazy_log/transformer.py
lazy_log/utils.py
lazy_log_formatter-0.11.0.dist-info/METADATA
lazy_log_formatter-0.11.0.dist-info/WHEEL
lazy_log_formatter-0.11.0.dist-info/entry_points.txt
lazy_log_formatter-0.11.0.dist-info/licenses/LICENSE
lazy_log_formatter-0.11.0.dist-info/RECORD
