Metadata-Version: 2.4
Name: lazy-log-formatter
Version: 0.11.0
Summary: A pre-commit script to make log lines lazier
License: MIT
License-File: LICENSE
Keywords: code-quality,f-strings,lazy logging,linting,logging,pre-commit,pylint,W1203
Author: Daniel Marín
Requires-Python: >=3.10
Classifier: Development Status :: 4 - Beta
Classifier: Intended Audience :: Developers
Classifier: License :: OSI Approved :: MIT License
Classifier: Natural Language :: English
Classifier: Programming Language :: Python :: 3
Classifier: Programming Language :: Python :: 3.10
Classifier: Programming Language :: Python :: 3.11
Classifier: Programming Language :: Python :: 3.12
Classifier: Programming Language :: Python :: 3.13
Classifier: Programming Language :: Python :: 3.14
Classifier: Topic :: Software Development :: Code Generators
Classifier: Topic :: Software Development :: Quality Assurance
Classifier: Topic :: Utilities
Requires-Dist: black (>=25.11.0,<26.0.0)
Requires-Dist: libcst (>=1.8.6,<2.0.0)
Project-URL: Homepage, https://github.com/dmar1n/lazy-log-formatter
Project-URL: Repository, https://github.com/dmar1n/lazy-log-formatter
